civics_cdf_validator/__init__.py
civics_cdf_validator/base.py
civics_cdf_validator/gpunit_rules.py
civics_cdf_validator/loggers.py
civics_cdf_validator/office_utils.py
civics_cdf_validator/rules.py
civics_cdf_validator/stats.py
civics_cdf_validator/validator.py
civics_cdf_validator/version.py
civics_cdf_validator-1.56.dist-info/licenses/LICENSE-2.0.txt
civics_cdf_validator-1.56.dist-info/METADATA
civics_cdf_validator-1.56.dist-info/WHEEL
civics_cdf_validator-1.56.dist-info/entry_points.txt
civics_cdf_validator-1.56.dist-info/top_level.txt
civics_cdf_validator-1.56.dist-info/RECORD
